paprika/__init__.py
paprika/benchmark.py
paprika/error_handling.py
paprika/oo.py
paprika/utility.py
paprika-1.3.0.dist-info/LICENSE
paprika-1.3.0.dist-info/WHEEL
paprika-1.3.0.dist-info/METADATA
paprika-1.3.0.dist-info/RECORD
