Metadata-Version: 2.1
Name: paprika
Version: 1.3.0
Summary: Paprika is a python library that reduces boilerplate. Heavily inspired by Project Lombok.
Home-page: https://github.com/rayanht/paprika
License: MIT
Author: Rayan Hatout
Author-email: rayan.hatout@gmail.com
Requires-Python: >=3.8,<4.0
Classifier: License :: OSI Approved :: MIT License
Classifier: Programming Language :: Python :: 3
Classifier: Programming Language :: Python :: 3.8
Classifier: Programming Language :: Python :: 3.9
Requires-Dist: tabulate (>=0.8.9,<0.9.0)
Project-URL: Repository, https://github.com/rayanht/paprika
